flask_exceptions/__init__.py
flask_exceptions/extension.py
Flask_Exceptions-1.2.3.dist-info/LICENSE.md
Flask_Exceptions-1.2.3.dist-info/METADATA
Flask_Exceptions-1.2.3.dist-info/WHEEL
Flask_Exceptions-1.2.3.dist-info/top_level.txt
Flask_Exceptions-1.2.3.dist-info/RECORD
